HISTORY.rst
MANIFEST.in
README.rst
setup.py
src/corbeau.py
src/corbeau.egg-info/PKG-INFO
src/corbeau.egg-info/SOURCES.txt
src/corbeau.egg-info/dependency_links.txt
src/corbeau.egg-info/requires.txt
src/corbeau.egg-info/top_level.txt