Metadata-Version: 1.0
Name: corbeau
Version: 0.2
Summary: A Sentry client based on Raven that verifies SSL certs
Home-page: https://github.com/kilink/corbeau
Author: Patrick Strawderman
Author-email: patrick@kilink.net
License: MIT
Platform: UNKNOWN
